handlers/__init__.py
handlers/base.py
handlers/file.py
handlers/http.py
handlers/llm.py
handlers/npm_install.py
handlers/pip_install.py
handlers/routine.py
handlers/shell.py
handlers/wait.py
tsuite/__init__.py
tsuite/cli.py
tsuite/client.py
tsuite/container_runner.py
tsuite/context.py
tsuite/db.py
tsuite/discovery.py
tsuite/docker_executor.py
tsuite/executor.py
tsuite/expressions.py
tsuite/models.py
tsuite/reporter.py
tsuite/repository.py
tsuite/routines.py
tsuite/scaffold.py
tsuite/server.py
tsuite/sse.py
tsuite/yaml_utils.py
tsuite/dashboard/.build-info
tsuite/dashboard/404.html
tsuite/dashboard/__next.__PAGE__.txt
tsuite/dashboard/__next._full.txt
tsuite/dashboard/__next._head.txt
tsuite/dashboard/__next._index.txt
tsuite/dashboard/__next._tree.txt
tsuite/dashboard/favicon.ico
tsuite/dashboard/file.svg
tsuite/dashboard/globe.svg
tsuite/dashboard/index.html
tsuite/dashboard/index.txt
tsuite/dashboard/next.svg
tsuite/dashboard/vercel.svg
tsuite/dashboard/window.svg
tsuite/dashboard/404/index.html
tsuite/dashboard/_next/static/8AEpwPxXf04hTmh7_9APb/_buildManifest.js
tsuite/dashboard/_next/static/8AEpwPxXf04hTmh7_9APb/_clientMiddlewareManifest.json
tsuite/dashboard/_next/static/8AEpwPxXf04hTmh7_9APb/_ssgManifest.js
tsuite/dashboard/_next/static/KSFAU5LOvD--UG2QGqCH3/_buildManifest.js
tsuite/dashboard/_next/static/KSFAU5LOvD--UG2QGqCH3/_clientMiddlewareManifest.json
tsuite/dashboard/_next/static/KSFAU5LOvD--UG2QGqCH3/_ssgManifest.js
tsuite/dashboard/_next/static/chunks/2b65fd3261100f07.js
tsuite/dashboard/_next/static/chunks/2c1533276e6a56e5.js
tsuite/dashboard/_next/static/chunks/31b244933736454f.js
tsuite/dashboard/_next/static/chunks/3d7fec13a34e99d9.css
tsuite/dashboard/_next/static/chunks/3eed4b3167217a49.js
tsuite/dashboard/_next/static/chunks/42c33ca704af9b68.js
tsuite/dashboard/_next/static/chunks/445e0822e17353b3.js
tsuite/dashboard/_next/static/chunks/55ded21150b18c31.js
tsuite/dashboard/_next/static/chunks/5e1ab6dba9472c07.js
mcp_mesh_tsuite-0.2.0.dist-info/METADATA
mcp_mesh_tsuite-0.2.0.dist-info/WHEEL
mcp_mesh_tsuite-0.2.0.dist-info/entry_points.txt
mcp_mesh_tsuite-0.2.0.dist-info/top_level.txt
mcp_mesh_tsuite-0.2.0.dist-info/RECORD
