Metadata-Version: 2.4
Name: mcp-mesh-tsuite
Version: 0.2.0
Summary: YAML-driven integration test framework with container isolation
Home-page: https://github.com/dhyansraj/mcp-mesh-test-suite
Author: MCP Mesh Team
License: MIT
Keywords: testing,integration-testing,yaml,docker,mcp-mesh
Classifier: Development Status :: 4 - Beta
Classifier: Intended Audience :: Developers
Classifier: License :: OSI Approved :: MIT License
Classifier: Programming Language :: Python :: 3
Classifier: Programming Language :: Python :: 3.10
Classifier: Programming Language :: Python :: 3.11
Classifier: Programming Language :: Python :: 3.12
Classifier: Topic :: Software Development :: Testing
Classifier: Topic :: Software Development :: Quality Assurance
Requires-Python: >=3.10
Requires-Dist: click>=8.0.0
Requires-Dist: pyyaml>=6.0
Requires-Dist: jsonpath-ng>=1.5.0
Requires-Dist: docker>=6.0.0
Requires-Dist: flask>=2.0.0
Requires-Dist: requests>=2.28.0
Requires-Dist: rich>=13.0.0
Dynamic: author
Dynamic: classifier
Dynamic: description
Dynamic: description-content-type
Dynamic: home-page
Dynamic: keywords
Dynamic: license
Dynamic: requires-dist
Dynamic: requires-python
Dynamic: summary
